uk_politics/__init__.py
uk_politics/colors.py
uk_politics/data_tables.py
uk_politics/elections.py
uk_politics/exceptions.py
uk_politics/location.py
uk_politics/names.py
uk_politics/data/GE_results.tsv
uk_politics/data/GE_results.tsv.license
uk_politics/data/party_colors.csv
uk_politics/data/party_colors.csv.license
uk_politics/data/party_nicknames.csv
uk_politics/data/party_nicknames.csv.license
uk_politics-1.0.5.dist-info/METADATA
uk_politics-1.0.5.dist-info/WHEEL
uk_politics-1.0.5.dist-info/top_level.txt
uk_politics-1.0.5.dist-info/RECORD
