Metadata-Version: 2.1
Name: uk-politics
Version: 1.0.5
Summary: United Kingdom political party names, colors, and election data
Home-page: https://github.com/Stonehaven-Campaigns/uk-politics-module
Maintainer: Stonehaven
Maintainer-email: data-accounts@stonehaven.uk.com
License: UNKNOWN
Keywords: politics elections uk parties
Platform: UNKNOWN
Classifier: Programming Language :: Python :: 3
Classifier: Programming Language :: Python :: 3.8
Requires-Dist: fuzzywuzzy
Requires-Dist: pandas
